chopchop/__init__.py
chopchop/core.py
lisachopchop-0.2.0.dist-info/LICENSE
lisachopchop-0.2.0.dist-info/METADATA
lisachopchop-0.2.0.dist-info/WHEEL
lisachopchop-0.2.0.dist-info/RECORD
