Metadata-Version: 2.3
Name: lisachopchop
Version: 0.2.0
Summary: Chop continuous stream of simulated data into more realistic LISA data packets
License: BSD 3-Clause License
Keywords: LISA,L2A,data delivery,data packet
Author: Jean-Baptiste Bayle
Author-email: j2b.bayle@gmail.com
Maintainer: Jean-Baptiste Bayle
Maintainer-email: j2b.bayle@gmail.com
Requires-Python: >=3.10,<4
Classifier: Intended Audience :: Science/Research
Classifier: Topic :: Scientific/Engineering :: Astronomy
Classifier: Topic :: Scientific/Engineering :: Physics
Requires-Dist: attrs (>=23.2.0,<24.0.0)
Requires-Dist: h5py (>=3.10.0,<4.0.0)
Requires-Dist: matplotlib (>=3.8.2,<4.0.0)
Requires-Dist: numpy (>=1.26.3,<2.0.0)
Requires-Dist: scipy (>=1.12.0,<2.0.0)
Project-URL: Documentation, https://lisa_irfu.pages.in2p3.fr/chopchop
Project-URL: Download, https://gitlab.in2p3.fr/lisa_irfu/chopchop/-/releases
Project-URL: Issue Tracker, https://gitlab.in2p3.fr/lisa_irfu/chopchop/-/issues
Project-URL: Repository, https://gitlab.in2p3.fr/lisa_irfu/chopchop
